shelvr/__init__.py
shelvr/cli.py
shelvr/log_config.py
shelvr-0.1.1.dist-info/METADATA
shelvr-0.1.1.dist-info/WHEEL
shelvr-0.1.1.dist-info/entry_points.txt
shelvr-0.1.1.dist-info/top_level.txt
shelvr-0.1.1.dist-info/RECORD
